{
 "version": "0",
 "homepage": "http://www.nirsoft.net/utils/acm.html",
 "url": "http://www.nirsoft.net/utils/acm.zip",
 "bin": "acm.exe",
 "hash": "tbd",
 "description": "Disable/enable ActiveX components on Internet Explorer browser.",
 "license": "Freeware",
 "notes": "If this application is useful to you, please consider donating to nirsoft.",
 "checkver": {
  "url": "http://www.nirsoft.net/pad/acm.xml",
  "re": "(?:<Program_Version>)(.*)(?:</Program_Version>)"
 },
 "autoupdate": {
  "url": "http://www.nirsoft.net/utils/acm.zip"
 }
}